[
  {
    "village_code": "25237",
    "village": "ABADIJAYA",
    "postal_code": "16417"
  },
  {
    "village_code": "25357",
    "village": "BAKTIJAYA",
    "postal_code": "16418"
  },
  {
    "village_code": "26776",
    "village": "CISALAK",
    "postal_code": "16416"
  },
  {
    "village_code": "28628",
    "village": "MEKARJAYA",
    "postal_code": "16411"
  },
  {
    "village_code": "30621",
    "village": "SUKMAJAYA",
    "postal_code": "16412"
  },
  {
    "village_code": "30958",
    "village": "TIRTAJAYA",
    "postal_code": "16412"
  }
]