[
  {
    "village_code": "31309",
    "village": "BAKULAN",
    "postal_code": "57362"
  },
  {
    "village_code": "32141",
    "village": "CABEAN KUNTI",
    "postal_code": "57362"
  },
  {
    "village_code": "32174",
    "village": "CANDIGATAK",
    "postal_code": "57362"
  },
  {
    "village_code": "32259",
    "village": "CEPOGO",
    "postal_code": "57362"
  },
  {
    "village_code": "32774",
    "village": "GEDANGAN",
    "postal_code": "57362"
  },
  {
    "village_code": "32886",
    "village": "GENTING",
    "postal_code": "57362"
  },
  {
    "village_code": "33112",
    "village": "GUBUG",
    "postal_code": "57362"
  },
  {
    "village_code": "33455",
    "village": "JELOK",
    "postal_code": "57362"
  },
  {
    "village_code": "33617",
    "village": "JOMBONG",
    "postal_code": "57362"
  },
  {
    "village_code": "34804",
    "village": "KEMBANG KUNING",
    "postal_code": "57362"
  },
  {
    "village_code": "35951",
    "village": "MLIWIS",
    "postal_code": "57362"
  },
  {
    "village_code": "36665",
    "village": "PARAS",
    "postal_code": "57362"
  },
  {
    "village_code": "38432",
    "village": "SUKABUMI",
    "postal_code": "57362"
  },
  {
    "village_code": "38568",
    "village": "SUMBUNG",
    "postal_code": "57362"
  },
  {
    "village_code": "39611",
    "village": "WONODOYO",
    "postal_code": "57362"
  }
]