[
  {
    "village_code": "31481",
    "village": "BANJARSARI",
    "postal_code": "52352"
  },
  {
    "village_code": "31514",
    "village": "BANTARBOLANG",
    "postal_code": "52352"
  },
  {
    "village_code": "32990",
    "village": "GLANDANG",
    "postal_code": "52352"
  },
  {
    "village_code": "34103",
    "village": "KARANGANYAR",
    "postal_code": "52352"
  },
  {
    "village_code": "34534",
    "village": "KEBON GEDE",
    "postal_code": "52352"
  },
  {
    "village_code": "35347",
    "village": "KUTA",
    "postal_code": "52352"
  },
  {
    "village_code": "35535",
    "village": "LENGGERONG",
    "postal_code": "52352"
  },
  {
    "village_code": "36392",
    "village": "PABUARAN",
    "postal_code": "52352"
  },
  {
    "village_code": "36477",
    "village": "PAGUYANGAN",
    "postal_code": "52352"
  },
  {
    "village_code": "36764",
    "village": "PEDAGUNG",
    "postal_code": "52352"
  },
  {
    "village_code": "36785",
    "village": "PEGIRINGAN",
    "postal_code": "52352"
  },
  {
    "village_code": "37304",
    "village": "PURANA",
    "postal_code": "52352"
  },
  {
    "village_code": "37616",
    "village": "SAMBENG",
    "postal_code": "52352"
  },
  {
    "village_code": "37731",
    "village": "SARWODADI",
    "postal_code": "52352"
  },
  {
    "village_code": "38589",
    "village": "SUMURKIDANG",
    "postal_code": "52352"
  },
  {
    "village_code": "38627",
    "village": "SURU",
    "postal_code": "52352"
  },
  {
    "village_code": "39427",
    "village": "WANARATA",
    "postal_code": "52352"
  }
]