[
  {
    "village_code": "21734",
    "village": "BANJAR AGUNG",
    "postal_code": "35365"
  },
  {
    "village_code": "22054",
    "village": "FAJAR BARU",
    "postal_code": "35365"
  },
  {
    "village_code": "22097",
    "village": "GEDUNG AGUNG",
    "postal_code": "35365"
  },
  {
    "village_code": "22109",
    "village": "GEDUNG HARAPAN",
    "postal_code": "35365"
  },
  {
    "village_code": "22284",
    "village": "JATIMULYO",
    "postal_code": "35365"
  },
  {
    "village_code": "22349",
    "village": "KARANG ANYAR",
    "postal_code": "35365"
  },
  {
    "village_code": "22364",
    "village": "KARANG REJO",
    "postal_code": "35365"
  },
  {
    "village_code": "22371",
    "village": "KARANG SARI",
    "postal_code": "35365"
  },
  {
    "village_code": "22657",
    "village": "MARGA / MARGO AGUNG",
    "postal_code": "35365"
  },
  {
    "village_code": "22650",
    "village": "MARGA KAYA",
    "postal_code": "35365"
  },
  {
    "village_code": "22664",
    "village": "MARGO DADI / DARI",
    "postal_code": "35365"
  },
  {
    "village_code": "22666",
    "village": "MARGO LESTARI",
    "postal_code": "35365"
  },
  {
    "village_code": "22669",
    "village": "MARGO REJO",
    "postal_code": "35365"
  },
  {
    "village_code": "22678",
    "village": "MARGOMULYO",
    "postal_code": "35365"
  },
  {
    "village_code": "23151",
    "village": "PURWOTANI",
    "postal_code": "35365"
  },
  {
    "village_code": "23220",
    "village": "REJOMULYO",
    "postal_code": "35365"
  },
  {
    "village_code": "23344",
    "village": "SIDOASRI (SIDODADI ASRI)",
    "postal_code": "35365"
  },
  {
    "village_code": "23359",
    "village": "SIDOHARJO",
    "postal_code": "35365"
  },
  {
    "village_code": "23432",
    "village": "SINAR REJEKI",
    "postal_code": "35365"
  },
  {
    "village_code": "23694",
    "village": "SUMBER JAYA",
    "postal_code": "35365"
  },
  {
    "village_code": "24093",
    "village": "WAY HUWI",
    "postal_code": "35365"
  }
]