[
  {
    "village_code": "559",
    "village": "BAROH BLANG MEE",
    "postal_code": "23354"
  },
  {
    "village_code": "563",
    "village": "BAROH GENTEUT",
    "postal_code": "23354"
  },
  {
    "village_code": "565",
    "village": "BAROH KRUENG KALA",
    "postal_code": "23354"
  },
  {
    "village_code": "727",
    "village": "BIREK",
    "postal_code": "23354"
  },
  {
    "village_code": "1453",
    "village": "COT",
    "postal_code": "23354"
  },
  {
    "village_code": "1463",
    "village": "CUNDIN",
    "postal_code": "23354"
  },
  {
    "village_code": "1812",
    "village": "GAPUY",
    "postal_code": "23354"
  },
  {
    "village_code": "1918",
    "village": "GLEE BRUEK",
    "postal_code": "23354"
  },
  {
    "village_code": "2133",
    "village": "JANTANG",
    "postal_code": "23354"
  },
  {
    "village_code": "2315",
    "village": "KAREUNG",
    "postal_code": "23354"
  },
  {
    "village_code": "2517",
    "village": "KEUTAPANG",
    "postal_code": "23354"
  },
  {
    "village_code": "2938",
    "village": "LAM GRIHEU",
    "postal_code": "23354"
  },
  {
    "village_code": "2944",
    "village": "LAM JUHANG",
    "postal_code": "23354"
  },
  {
    "village_code": "2951",
    "village": "LAM KUTA BLANG MEE",
    "postal_code": "23354"
  },
  {
    "village_code": "2974",
    "village": "LAM SUJEN",
    "postal_code": "23354"
  },
  {
    "village_code": "3935",
    "village": "MEUNASAH KRUENG KALA",
    "postal_code": "23354"
  },
  {
    "village_code": "3956",
    "village": "MEUNASAH LHOK",
    "postal_code": "23354"
  },
  {
    "village_code": "4112",
    "village": "MON MATA",
    "postal_code": "23354"
  },
  {
    "village_code": "4475",
    "village": "PAROY",
    "postal_code": "23354"
  },
  {
    "village_code": "4537",
    "village": "PASIE",
    "postal_code": "23354"
  },
  {
    "village_code": "4863",
    "village": "PUDENG",
    "postal_code": "23354"
  },
  {
    "village_code": "5276",
    "village": "SANEY",
    "postal_code": "23354"
  },
  {
    "village_code": "5347",
    "village": "SENGKO MEULAT",
    "postal_code": "23354"
  },
  {
    "village_code": "6023",
    "village": "TEUNGOH BLANG MEE",
    "postal_code": "23354"
  },
  {
    "village_code": "6026",
    "village": "TEUNGOH GEUNTEUT",
    "postal_code": "23354"
  },
  {
    "village_code": "6188",
    "village": "TUNONG KRUENG KALA",
    "postal_code": "23354"
  },
  {
    "village_code": "6384",
    "village": "UMONG SEUREBEE",
    "postal_code": "23354"
  },
  {
    "village_code": "6403",
    "village": "UTAMONG",
    "postal_code": "23354"
  }
]