[
  {
    "village_code": "26107",
    "village": "CIGAWIR",
    "postal_code": "44187"
  },
  {
    "village_code": "26738",
    "village": "CIRAPUHAN",
    "postal_code": "44187"
  },
  {
    "village_code": "28702",
    "village": "MEKARSARI",
    "postal_code": "44187"
  },
  {
    "village_code": "29417",
    "village": "PELITA ASIH",
    "postal_code": "44187"
  },
  {
    "village_code": "29537",
    "village": "PUTRAJAWA",
    "postal_code": "44187"
  },
  {
    "village_code": "29710",
    "village": "SAMIDA",
    "postal_code": "44187"
  },
  {
    "village_code": "29793",
    "village": "SELAAWI",
    "postal_code": "44187"
  }
]