[
  {
    "village_code": "74867",
    "village": "AIBORE",
    "postal_code": "98854"
  },
  {
    "village_code": "75803",
    "village": "EPOMANI",
    "postal_code": "98854"
  },
  {
    "village_code": "77071",
    "village": "MABUA  /  MABOU",
    "postal_code": "98854"
  },
  {
    "village_code": "78367",
    "village": "SIRIWO (UNIPO)",
    "postal_code": "98854"
  },
  {
    "village_code": "78647",
    "village": "TIBAI",
    "postal_code": "98854"
  },
  {
    "village_code": "78815",
    "village": "UGIDA",
    "postal_code": "98854"
  }
]