[
  {
    "village_code": "20339",
    "village": "DESA GAJAH MATI",
    "postal_code": "38382"
  },
  {
    "village_code": "20342",
    "village": "DESA SEMIDANG",
    "postal_code": "38382"
  },
  {
    "village_code": "20349",
    "village": "DURIAN DEMANG",
    "postal_code": "38382"
  },
  {
    "village_code": "20357",
    "village": "DUSUN BARU II",
    "postal_code": "38382"
  },
  {
    "village_code": "20481",
    "village": "KANCING",
    "postal_code": "38382"
  },
  {
    "village_code": "20503",
    "village": "KARANG NANDING",
    "postal_code": "38382"
  },
  {
    "village_code": "20511",
    "village": "KARANG TINGGI",
    "postal_code": "38382"
  },
  {
    "village_code": "20838",
    "village": "PADANG SIRING",
    "postal_code": "38382"
  },
  {
    "village_code": "20840",
    "village": "PADANG TAMBAK",
    "postal_code": "38382"
  },
  {
    "village_code": "20862",
    "village": "PAGAR GUNUNG",
    "postal_code": "38382"
  },
  {
    "village_code": "20952",
    "village": "PENANDING",
    "postal_code": "38382"
  },
  {
    "village_code": "20988",
    "village": "PLAJU (PELAJAU)",
    "postal_code": "38382"
  },
  {
    "village_code": "21040",
    "village": "RENA LEBAR",
    "postal_code": "38382"
  },
  {
    "village_code": "21041",
    "village": "RENA SEMANEK",
    "postal_code": "38382"
  },
  {
    "village_code": "21279",
    "village": "TABA MUTUNG",
    "postal_code": "38382"
  },
  {
    "village_code": "21294",
    "village": "TABA TERUNJAM",
    "postal_code": "38382"
  },
  {
    "village_code": "21334",
    "village": "TALANG EMPAT",
    "postal_code": "38385"
  },
  {
    "village_code": "21568",
    "village": "UJUNG KARANG",
    "postal_code": "38382"
  }
]