[
  {
    "village_code": "12517",
    "village": "BATU BASA",
    "postal_code": "27264"
  },
  {
    "village_code": "13107",
    "village": "PARIANGAN",
    "postal_code": "27264"
  },
  {
    "village_code": "13233",
    "village": "SAWAH TANGAH",
    "postal_code": "27264"
  },
  {
    "village_code": "13285",
    "village": "SIMABUR",
    "postal_code": "27264"
  },
  {
    "village_code": "13357",
    "village": "SUNGAI JAMBU",
    "postal_code": "27264"
  },
  {
    "village_code": "13408",
    "village": "TABEK",
    "postal_code": "27264"
  }
]