[
  {
    "village_code": "31544",
    "village": "BANYUKEMBAR",
    "postal_code": "56352"
  },
  {
    "village_code": "31772",
    "village": "BINANGUN",
    "postal_code": "56352"
  },
  {
    "village_code": "32110",
    "village": "BUMIROSO",
    "postal_code": "56352"
  },
  {
    "village_code": "33038",
    "village": "GONDANG",
    "postal_code": "56352"
  },
  {
    "village_code": "33123",
    "village": "GUMAWANG KIDUL",
    "postal_code": "56352"
  },
  {
    "village_code": "33805",
    "village": "KALIDESEL",
    "postal_code": "56352"
  },
  {
    "village_code": "35259",
    "village": "KRINJING",
    "postal_code": "56352"
  },
  {
    "village_code": "35344",
    "village": "KURIPAN",
    "postal_code": "56352"
  },
  {
    "village_code": "35562",
    "village": "LIMBANGAN",
    "postal_code": "56352"
  },
  {
    "village_code": "35613",
    "village": "LUMAJANG",
    "postal_code": "56352"
  },
  {
    "village_code": "36088",
    "village": "MUTISARI",
    "postal_code": "56352"
  },
  {
    "village_code": "36720",
    "village": "PASURUHAN",
    "postal_code": "56352"
  },
  {
    "village_code": "39505",
    "village": "WATUMALANG",
    "postal_code": "56352"
  },
  {
    "village_code": "39620",
    "village": "WONOKAMPIR",
    "postal_code": "56352"
  },
  {
    "village_code": "39669",
    "village": "WONOROTO",
    "postal_code": "56352"
  },
  {
    "village_code": "39700",
    "village": "WONOSROYO",
    "postal_code": "56352"
  }
]