[
  {
    "village_code": "7197",
    "village": "BONANDOLOK",
    "postal_code": "22611"
  },
  {
    "village_code": "9011",
    "village": "MARDAME",
    "postal_code": "22611"
  },
  {
    "village_code": "9232",
    "village": "NAGA TIMBUL",
    "postal_code": "22611"
  },
  {
    "village_code": "9322",
    "village": "NAULI",
    "postal_code": "22611"
  },
  {
    "village_code": "10398",
    "village": "RAMPA",
    "postal_code": "22611"
  },
  {
    "village_code": "11272",
    "village": "SIMANINGGIR",
    "postal_code": "22611"
  }
]