[
  {
    "village_code": "74849",
    "village": "AGAIN",
    "postal_code": "99562"
  },
  {
    "village_code": "75271",
    "village": "BAWI",
    "postal_code": "99562"
  },
  {
    "village_code": "76411",
    "village": "KAIGA",
    "postal_code": "99562"
  },
  {
    "village_code": "76797",
    "village": "KOTORAMBUR",
    "postal_code": "99562"
  },
  {
    "village_code": "76885",
    "village": "KURBAYA",
    "postal_code": "99562"
  },
  {
    "village_code": "77935",
    "village": "PIRALEME",
    "postal_code": "99562"
  },
  {
    "village_code": "78677",
    "village": "TINA",
    "postal_code": "99562"
  },
  {
    "village_code": "78791",
    "village": "TUNGGUNALE",
    "postal_code": "99562"
  },
  {
    "village_code": "79248",
    "village": "WIYANGGER",
    "postal_code": "99562"
  },
  {
    "village_code": "79272",
    "village": "WOLU",
    "postal_code": "99562"
  }
]