[
  {
    "village_code": "7446",
    "village": "DURIAN",
    "postal_code": "20235"
  },
  {
    "village_code": "7522",
    "village": "GAHARU",
    "postal_code": "20235"
  },
  {
    "village_code": "7538",
    "village": "GANG BUNTU",
    "postal_code": "20231"
  },
  {
    "village_code": "7561",
    "village": "GLUGUR DARAT I",
    "postal_code": "20238"
  },
  {
    "village_code": "7562",
    "village": "GLUGUR DARAT II",
    "postal_code": "20238"
  },
  {
    "village_code": "10106",
    "village": "PERINTIS",
    "postal_code": "20231"
  },
  {
    "village_code": "10311",
    "village": "PULO BRAYAN BENGKEL",
    "postal_code": "20239"
  },
  {
    "village_code": "10310",
    "village": "PULO BRAYAN BENGKEL BARU",
    "postal_code": "20239"
  },
  {
    "village_code": "10312",
    "village": "PULO BRAYAN DARAT I",
    "postal_code": "20239"
  },
  {
    "village_code": "10313",
    "village": "PULO BRAYAN DARAT II",
    "postal_code": "20239"
  },
  {
    "village_code": "10970",
    "village": "SIDODADI",
    "postal_code": "20234"
  }
]