[
  {
    "village_code": "66313",
    "village": "BENTENG KADO TO\\RIA",
    "postal_code": "91833"
  },
  {
    "village_code": "66682",
    "village": "BUNTU BARANA",
    "postal_code": "91833"
  },
  {
    "village_code": "66686",
    "village": "BUNTU BATU",
    "postal_code": "91833"
  },
  {
    "village_code": "66826",
    "village": "EMBATAU",
    "postal_code": "91833"
  },
  {
    "village_code": "67928",
    "village": "PANGDEN",
    "postal_code": "91833"
  },
  {
    "village_code": "68436",
    "village": "SEREALE",
    "postal_code": "91833"
  },
  {
    "village_code": "68762",
    "village": "TIKALA",
    "postal_code": "91833"
  }
]