[
  {
    "village_code": "17489",
    "village": "GUNUNG KEMALA",
    "postal_code": "31122"
  },
  {
    "village_code": "18354",
    "village": "MUNTANG TAPUS",
    "postal_code": "31121"
  },
  {
    "village_code": "18573",
    "village": "PATIH GALUNG",
    "postal_code": "31127"
  },
  {
    "village_code": "18585",
    "village": "PAYU PUTAT",
    "postal_code": "31141"
  },
  {
    "village_code": "18732",
    "village": "PRABUMULIH",
    "postal_code": "31123"
  },
  {
    "village_code": "19826",
    "village": "TANJUNG TELANG",
    "postal_code": "31146"
  }
]