[
  {
    "village_code": "66158",
    "village": "BAMBA PUANG",
    "postal_code": "91752"
  },
  {
    "village_code": "66261",
    "village": "BATU NONI",
    "postal_code": "91752"
  },
  {
    "village_code": "66616",
    "village": "BUBUN LAMBA",
    "postal_code": "91752"
  },
  {
    "village_code": "67167",
    "village": "LAKAWAN",
    "postal_code": "91752"
  },
  {
    "village_code": "67505",
    "village": "MAMPU",
    "postal_code": "91752"
  },
  {
    "village_code": "67515",
    "village": "MANDATTE",
    "postal_code": "91752"
  },
  {
    "village_code": "67643",
    "village": "MATARAN",
    "postal_code": "91752"
  },
  {
    "village_code": "68077",
    "village": "PEKALOBEAN",
    "postal_code": "91752"
  },
  {
    "village_code": "68320",
    "village": "SALU DEWATA",
    "postal_code": "91752"
  },
  {
    "village_code": "68399",
    "village": "SARURAN",
    "postal_code": "91752"
  },
  {
    "village_code": "68444",
    "village": "SIAMBO",
    "postal_code": "91752"
  },
  {
    "village_code": "68471",
    "village": "SINGKI",
    "postal_code": "91752"
  },
  {
    "village_code": "68627",
    "village": "TAMPO",
    "postal_code": "91752"
  },
  {
    "village_code": "68655",
    "village": "TANETE",
    "postal_code": "91752"
  },
  {
    "village_code": "68773",
    "village": "TINDALLUN",
    "postal_code": "91752"
  }
]