[
  {
    "village_code": "20279",
    "village": "BUKIT NIBUNG",
    "postal_code": "39262"
  },
  {
    "village_code": "20298",
    "village": "BUNGIN",
    "postal_code": "39262"
  },
  {
    "village_code": "20497",
    "village": "KARANG DAPO ATAS",
    "postal_code": "39262"
  },
  {
    "village_code": "20498",
    "village": "KARANG DAPO BAWAH",
    "postal_code": "39262"
  },
  {
    "village_code": "20935",
    "village": "PELABUHAN TALANG LEAK",
    "postal_code": "39262"
  },
  {
    "village_code": "21019",
    "village": "PUNGGUK PEDARO",
    "postal_code": "39262"
  },
  {
    "village_code": "21349",
    "village": "TALANG KERINCI",
    "postal_code": "39262"
  },
  {
    "village_code": "21353",
    "village": "TALANG LEAK I",
    "postal_code": "39262"
  },
  {
    "village_code": "21354",
    "village": "TALANG LEAK II",
    "postal_code": "39262"
  }
]