[
  {
    "village_code": "40232",
    "village": "AMBAT",
    "postal_code": "69371"
  },
  {
    "village_code": "40494",
    "village": "BANDARAN",
    "postal_code": "69371"
  },
  {
    "village_code": "41123",
    "village": "BRANTA PASISIR",
    "postal_code": "69371"
  },
  {
    "village_code": "41124",
    "village": "BRANTA TINGGI",
    "postal_code": "69371"
  },
  {
    "village_code": "41185",
    "village": "BUKEK",
    "postal_code": "69371"
  },
  {
    "village_code": "41384",
    "village": "CEGUK",
    "postal_code": "69371"
  },
  {
    "village_code": "41484",
    "village": "DABUAN",
    "postal_code": "69371"
  },
  {
    "village_code": "42148",
    "village": "GUGUL",
    "postal_code": "69371"
  },
  {
    "village_code": "43886",
    "village": "KRAMAT",
    "postal_code": "69371"
  },
  {
    "village_code": "44080",
    "village": "LARANGAN SLAMPAR",
    "postal_code": "69371"
  },
  {
    "village_code": "44083",
    "village": "LARANGAN TOKOL",
    "postal_code": "69371"
  },
  {
    "village_code": "44295",
    "village": "MANGAR",
    "postal_code": "69371"
  },
  {
    "village_code": "45378",
    "village": "PANGLEGUR",
    "postal_code": "69371"
  },
  {
    "village_code": "47898",
    "village": "TARO\\AN",
    "postal_code": "69371"
  },
  {
    "village_code": "48096",
    "village": "TERRAK",
    "postal_code": "69371"
  },
  {
    "village_code": "48144",
    "village": "TLANAKAN",
    "postal_code": "69371"
  },
  {
    "village_code": "48151",
    "village": "TLESA",
    "postal_code": "69371"
  }
]