[
  {
    "village_code": "55313",
    "village": "BANJAR",
    "postal_code": "78822"
  },
  {
    "village_code": "55327",
    "village": "BARU",
    "postal_code": "78822"
  },
  {
    "village_code": "55694",
    "village": "KAUMAN",
    "postal_code": "78821"
  },
  {
    "village_code": "55767",
    "village": "KINJIL PESISIR",
    "postal_code": "78822"
  },
  {
    "village_code": "55961",
    "village": "MEKAR SARI",
    "postal_code": "78822"
  },
  {
    "village_code": "56052",
    "village": "MULIA KERTA",
    "postal_code": "78822"
  },
  {
    "village_code": "56197",
    "village": "NEGERI BARU",
    "postal_code": "78822"
  },
  {
    "village_code": "56226",
    "village": "PADANG",
    "postal_code": "78822"
  },
  {
    "village_code": "56625",
    "village": "SEI / SUNGAI KINJIL",
    "postal_code": "78822"
  },
  {
    "village_code": "56899",
    "village": "SUKA BARU",
    "postal_code": "78822"
  },
  {
    "village_code": "57179",
    "village": "TUAN TUAN",
    "postal_code": "78822"
  }
]