[
  {
    "village_code": "60820",
    "village": "BATU AMPAR",
    "postal_code": "76136"
  },
  {
    "village_code": "60957",
    "village": "GRAHA INDAH",
    "postal_code": "76129"
  },
  {
    "village_code": "60970",
    "village": "GUNUNG SAMARINDA",
    "postal_code": "76125"
  },
  {
    "village_code": "60969",
    "village": "GUNUNG SAMARINDA BARU",
    "postal_code": "76128"
  },
  {
    "village_code": "61035",
    "village": "KARANG JOANG",
    "postal_code": "76127"
  },
  {
    "village_code": "61350",
    "village": "MUARA RAPAK",
    "postal_code": "76125"
  }
]