[
  {
    "village_code": "12621",
    "village": "EKOR LUBUK",
    "postal_code": "27125"
  },
  {
    "village_code": "12632",
    "village": "GANTING",
    "postal_code": "27127"
  },
  {
    "village_code": "12645",
    "village": "GUGUK MALINTANG",
    "postal_code": "27128"
  },
  {
    "village_code": "12793",
    "village": "KOTO KATIK",
    "postal_code": "27123"
  },
  {
    "village_code": "12813",
    "village": "KOTO PANJANG",
    "postal_code": "27122"
  },
  {
    "village_code": "13025",
    "village": "NGALAU",
    "postal_code": "27124"
  },
  {
    "village_code": "13258",
    "village": "SIGANDO",
    "postal_code": "27126"
  },
  {
    "village_code": "13445",
    "village": "TANAH PAK LAMBIK",
    "postal_code": "27121"
  }
]