[
  {
    "village_code": "6554",
    "village": "AEK NGALI",
    "postal_code": "22952"
  },
  {
    "village_code": "7766",
    "village": "HAYURAJA",
    "postal_code": "22952"
  },
  {
    "village_code": "8177",
    "village": "HUTARAJA HUTAJULU",
    "postal_code": "22952"
  },
  {
    "village_code": "8182",
    "village": "HUTARIMBARU",
    "postal_code": "22952"
  },
  {
    "village_code": "8383",
    "village": "KAYU LAUT",
    "postal_code": "22952"
  },
  {
    "village_code": "8857",
    "village": "LUMBAN DOLOK",
    "postal_code": "22952"
  },
  {
    "village_code": "9512",
    "village": "PAGARAN GALA-GALA",
    "postal_code": "22952"
  },
  {
    "village_code": "10450",
    "village": "ROBURAN DOLOK",
    "postal_code": "22952"
  },
  {
    "village_code": "10451",
    "village": "ROBURAN LOMBANG",
    "postal_code": "22952"
  },
  {
    "village_code": "12047",
    "village": "TANO BATO",
    "postal_code": "22952"
  }
]