[
  {
    "village_code": "16931",
    "village": "1 ULU",
    "postal_code": "30257"
  },
  {
    "village_code": "16941",
    "village": "15 ULU",
    "postal_code": "30257"
  },
  {
    "village_code": "16948",
    "village": "2 ULU",
    "postal_code": "30257"
  },
  {
    "village_code": "16962",
    "village": "3-4 ULU",
    "postal_code": "30255"
  },
  {
    "village_code": "16968",
    "village": "5 ULU",
    "postal_code": "30254"
  },
  {
    "village_code": "16969",
    "village": "7 ULU",
    "postal_code": "30253"
  },
  {
    "village_code": "16971",
    "village": "8 ULU",
    "postal_code": "30252"
  },
  {
    "village_code": "16973",
    "village": "9 / 10 ULU",
    "postal_code": "30251"
  },
  {
    "village_code": "19049",
    "village": "SILABERANTI",
    "postal_code": "30251"
  },
  {
    "village_code": "19957",
    "village": "TUAN KENTANG",
    "postal_code": "30251"
  }
]