[
  {
    "village_code": "31446",
    "village": "BANJARANYAR",
    "postal_code": "52216"
  },
  {
    "village_code": "31965",
    "village": "BREBES",
    "postal_code": "52212"
  },
  {
    "village_code": "32711",
    "village": "GANDASULI",
    "postal_code": "52215"
  },
  {
    "village_code": "33810",
    "village": "KALIGANGSA KULON",
    "postal_code": "52217"
  },
  {
    "village_code": "33811",
    "village": "KALIGANGSA WETAN",
    "postal_code": "52217"
  },
  {
    "village_code": "33887",
    "village": "KALIMATI",
    "postal_code": "52219"
  },
  {
    "village_code": "34005",
    "village": "KALIWLINGI",
    "postal_code": "52219"
  },
  {
    "village_code": "34745",
    "village": "KEDUNGUTER",
    "postal_code": "52219"
  },
  {
    "village_code": "35226",
    "village": "KRASAK",
    "postal_code": "52219"
  },
  {
    "village_code": "35526",
    "village": "LEMBARAWA",
    "postal_code": "52219"
  },
  {
    "village_code": "35551",
    "village": "LIMBANGAN KULON",
    "postal_code": "52219"
  },
  {
    "village_code": "35552",
    "village": "LIMBANGAN WETAN",
    "postal_code": "52218"
  },
  {
    "village_code": "36420",
    "village": "PADASUGIH",
    "postal_code": "52214"
  },
  {
    "village_code": "36436",
    "village": "PAGEJUGAN",
    "postal_code": "52219"
  },
  {
    "village_code": "36679",
    "village": "PASAR BATANG",
    "postal_code": "52211"
  },
  {
    "village_code": "36843",
    "village": "PEMARON",
    "postal_code": "52219"
  },
  {
    "village_code": "37271",
    "village": "PULOSARI",
    "postal_code": "52213"
  },
  {
    "village_code": "37447",
    "village": "RANDUSANGA KULON",
    "postal_code": "52219"
  },
  {
    "village_code": "37448",
    "village": "RANDUSANGA WETAN",
    "postal_code": "52219"
  },
  {
    "village_code": "38135",
    "village": "SIGAMBIR",
    "postal_code": "52219"
  },
  {
    "village_code": "39056",
    "village": "TENGKI",
    "postal_code": "52219"
  },
  {
    "village_code": "39076",
    "village": "TERLANGU",
    "postal_code": "52219"
  },
  {
    "village_code": "39438",
    "village": "WANGANDALEM",
    "postal_code": "52214"
  }
]