[
  {
    "village_code": "40703",
    "village": "BANYUURIP",
    "postal_code": "61154"
  },
  {
    "village_code": "41070",
    "village": "BOLO",
    "postal_code": "61154"
  },
  {
    "village_code": "41352",
    "village": "CANGAAN",
    "postal_code": "61154"
  },
  {
    "village_code": "42055",
    "village": "GLATIK",
    "postal_code": "61154"
  },
  {
    "village_code": "42110",
    "village": "GOSARI",
    "postal_code": "61154"
  },
  {
    "village_code": "43036",
    "village": "KARANGREJO",
    "postal_code": "61154"
  },
  {
    "village_code": "43204",
    "village": "KEBONAGUNG",
    "postal_code": "61154"
  },
  {
    "village_code": "43688",
    "village": "KETAPANG LOR",
    "postal_code": "61154"
  },
  {
    "village_code": "44863",
    "village": "NGEMBOH",
    "postal_code": "61154"
  },
  {
    "village_code": "45370",
    "village": "PANGKAH KULON",
    "postal_code": "61154"
  },
  {
    "village_code": "45371",
    "village": "PANGKAH WETAN",
    "postal_code": "61154"
  },
  {
    "village_code": "46477",
    "village": "SEKAPUK",
    "postal_code": "61154"
  },
  {
    "village_code": "47825",
    "village": "TANJANGAWAN",
    "postal_code": "61154"
  }
]