[
  {
    "village_code": "15392",
    "village": "AIR MUMU",
    "postal_code": "37174"
  },
  {
    "village_code": "15603",
    "village": "DUSUN BARU LEMPUR",
    "postal_code": "37174"
  },
  {
    "village_code": "15720",
    "village": "KEBUN BARU",
    "postal_code": "37174"
  },
  {
    "village_code": "15723",
    "village": "KEBUN LIMA",
    "postal_code": "37174"
  },
  {
    "village_code": "15879",
    "village": "LEMPUR HILIR",
    "postal_code": "37174"
  },
  {
    "village_code": "15880",
    "village": "LEMPUR MUDIK",
    "postal_code": "37174"
  },
  {
    "village_code": "15881",
    "village": "LEMPUR TENGAH",
    "postal_code": "37174"
  },
  {
    "village_code": "15954",
    "village": "MANJUNTO LEMPUR",
    "postal_code": "37174"
  },
  {
    "village_code": "15964",
    "village": "MASGO",
    "postal_code": "37174"
  },
  {
    "village_code": "16240",
    "village": "PERIKAN TENGAH",
    "postal_code": "37174"
  },
  {
    "village_code": "16429",
    "village": "SELAMPAUNG",
    "postal_code": "37174"
  },
  {
    "village_code": "16605",
    "village": "SUNGAI HANGAT",
    "postal_code": "37174"
  }
]