[
  {
    "village_code": "79971",
    "village": "GAG",
    "postal_code": "98481"
  },
  {
    "village_code": "80387",
    "village": "MANYAIFUN",
    "postal_code": "98481"
  },
  {
    "village_code": "80453",
    "village": "MEOSMANGGARA",
    "postal_code": "98481"
  },
  {
    "village_code": "80598",
    "village": "PAM",
    "postal_code": "98481"
  },
  {
    "village_code": "80710",
    "village": "SAUKABU",
    "postal_code": "98481"
  },
  {
    "village_code": "80711",
    "village": "SAUPAPIR",
    "postal_code": "98481"
  }
]