[
  {
    "village_code": "55376",
    "village": "BELIMBING",
    "postal_code": "78774"
  },
  {
    "village_code": "55495",
    "village": "DANGKAN KOTA",
    "postal_code": "78774"
  },
  {
    "village_code": "55553",
    "village": "ENTEBI",
    "postal_code": "78774"
  },
  {
    "village_code": "55825",
    "village": "LANDAU BADAI",
    "postal_code": "78774"
  },
  {
    "village_code": "55838",
    "village": "LANDAU RANTAU",
    "postal_code": "78774"
  },
  {
    "village_code": "55851",
    "village": "LEBAK NAJAH",
    "postal_code": "78774"
  },
  {
    "village_code": "56076",
    "village": "NANGA DANGKAN I",
    "postal_code": "78774"
  },
  {
    "village_code": "56114",
    "village": "NANGA LUAN",
    "postal_code": "78774"
  },
  {
    "village_code": "56115",
    "village": "NANGA LUNGU",
    "postal_code": "78774"
  },
  {
    "village_code": "56131",
    "village": "NANGA NGERI",
    "postal_code": "78774"
  },
  {
    "village_code": "56376",
    "village": "PERJUK",
    "postal_code": "78774"
  },
  {
    "village_code": "56471",
    "village": "RIAM TAPANG",
    "postal_code": "78774"
  },
  {
    "village_code": "56725",
    "village": "SELANGKAI",
    "postal_code": "78774"
  },
  {
    "village_code": "56731",
    "village": "SELIMU",
    "postal_code": "78774"
  }
]