[
  {
    "village_code": "66057",
    "village": "APPANANG",
    "postal_code": "90861"
  },
  {
    "village_code": "66196",
    "village": "BARANG",
    "postal_code": "90861"
  },
  {
    "village_code": "66845",
    "village": "GALUNG",
    "postal_code": "90861"
  },
  {
    "village_code": "66906",
    "village": "JAMPU",
    "postal_code": "90861"
  },
  {
    "village_code": "66918",
    "village": "JENNAE",
    "postal_code": "90861"
  },
  {
    "village_code": "68064",
    "village": "PATTOJO",
    "postal_code": "90861"
  },
  {
    "village_code": "68268",
    "village": "ROMPEGADING",
    "postal_code": "90861"
  },
  {
    "village_code": "68770",
    "village": "TIMUSU",
    "postal_code": "90861"
  }
]