[
  {
    "village_code": "25434",
    "village": "BANTARDAWA",
    "postal_code": "46385"
  },
  {
    "village_code": "27758",
    "village": "KARANGPANINGAL",
    "postal_code": "46385"
  },
  {
    "village_code": "28164",
    "village": "KUTAWARINGIN",
    "postal_code": "46385"
  },
  {
    "village_code": "28985",
    "village": "PADARINGAN",
    "postal_code": "46385"
  },
  {
    "village_code": "29344",
    "village": "PASIRLAWANG",
    "postal_code": "46385"
  },
  {
    "village_code": "29491",
    "village": "PURWADADI",
    "postal_code": "46385"
  },
  {
    "village_code": "29496",
    "village": "PURWAJAYA",
    "postal_code": "46385"
  },
  {
    "village_code": "29868",
    "village": "SIDARAHAYU",
    "postal_code": "46385"
  },
  {
    "village_code": "30434",
    "village": "SUKAMULYA",
    "postal_code": "46385"
  }
]