[
  {
    "village_code": "75085",
    "village": "ARURI",
    "postal_code": "98161"
  },
  {
    "village_code": "76246",
    "village": "IMBRISBARI (IMBIRSBARI)",
    "postal_code": "98161"
  },
  {
    "village_code": "76264",
    "village": "INEKI",
    "postal_code": "98161"
  },
  {
    "village_code": "76279",
    "village": "INSUMBREI",
    "postal_code": "98161"
  },
  {
    "village_code": "77167",
    "village": "MANGGONSWAN (MANGOSWAN)",
    "postal_code": "98161"
  },
  {
    "village_code": "77253",
    "village": "MBRUWANDI (BRUWANDI)",
    "postal_code": "98161"
  },
  {
    "village_code": "78069",
    "village": "RAYORI",
    "postal_code": "98161"
  },
  {
    "village_code": "79289",
    "village": "WONGGEINA (WONGKEINA)",
    "postal_code": "98161"
  },
  {
    "village_code": "79449",
    "village": "YAMNAISU",
    "postal_code": "98161"
  }
]