[
  {
    "village_code": "64638",
    "village": "KHATULISTIWA",
    "postal_code": "94475"
  },
  {
    "village_code": "64927",
    "village": "MALANGGO (MALGGO)",
    "postal_code": "94475"
  },
  {
    "village_code": "64928",
    "village": "MALANGGO PESISIR",
    "postal_code": "94475"
  },
  {
    "village_code": "64971",
    "village": "MANINILI",
    "postal_code": "94475"
  },
  {
    "village_code": "64969",
    "village": "MANINILI BARAT",
    "postal_code": "94475"
  },
  {
    "village_code": "64970",
    "village": "MANINILI UTARA",
    "postal_code": "94475"
  },
  {
    "village_code": "65328",
    "village": "POLLY",
    "postal_code": "94475"
  },
  {
    "village_code": "65493",
    "village": "SIAGA",
    "postal_code": "94475"
  },
  {
    "village_code": "65530",
    "village": "SIGENTI",
    "postal_code": "94475"
  },
  {
    "village_code": "65527",
    "village": "SIGENTI BARAT",
    "postal_code": "94475"
  },
  {
    "village_code": "65528",
    "village": "SIGENTI BERSEHATI",
    "postal_code": "94475"
  },
  {
    "village_code": "65529",
    "village": "SIGENTI SELATAN",
    "postal_code": "94475"
  },
  {
    "village_code": "65541",
    "village": "SILUTUNG",
    "postal_code": "94475"
  },
  {
    "village_code": "65554",
    "village": "SINEI",
    "postal_code": "94475"
  },
  {
    "village_code": "65555",
    "village": "SINEY TENGAH",
    "postal_code": "94475"
  },
  {
    "village_code": "65623",
    "village": "TADA",
    "postal_code": "94475"
  },
  {
    "village_code": "65620",
    "village": "TADA SELATAN",
    "postal_code": "94475"
  },
  {
    "village_code": "65621",
    "village": "TADA TIMUR",
    "postal_code": "94475"
  },
  {
    "village_code": "65622",
    "village": "TADA UTARA",
    "postal_code": "94475"
  }
]