[
  {
    "village_code": "14072",
    "village": "KOTA BARU",
    "postal_code": "28114"
  },
  {
    "village_code": "14084",
    "village": "KOTA TINGGI",
    "postal_code": "28112"
  },
  {
    "village_code": "14900",
    "village": "SIMPANG EMPAT",
    "postal_code": "28116"
  },
  {
    "village_code": "14967",
    "village": "SUKA RAMAI",
    "postal_code": "28111"
  },
  {
    "village_code": "14981",
    "village": "SUMA HILANG",
    "postal_code": "28111"
  },
  {
    "village_code": "15142",
    "village": "TANAH DATAR",
    "postal_code": "28115"
  }
]