[
  {
    "village_code": "66205",
    "village": "BARING",
    "postal_code": "90655"
  },
  {
    "village_code": "66292",
    "village": "BAWASALO",
    "postal_code": "90655"
  },
  {
    "village_code": "66406",
    "village": "BONE",
    "postal_code": "90655"
  },
  {
    "village_code": "66471",
    "village": "BONTO MATENE",
    "postal_code": "90655"
  },
  {
    "village_code": "67982",
    "village": "PARENRENG",
    "postal_code": "90655"
  },
  {
    "village_code": "68424",
    "village": "SEGERI",
    "postal_code": "90655"
  }
]